scaae/.DS_Store
scaae/__init__.py
scaae/__main__.py
scaae/analyses.py
scaae/callbacks.py
scaae/cli.py
scaae/statistics.py
scaae/utilities.py
scaae/data/__init__.py
scaae/data/preprocessing.py
scaae/data/reading.py
scaae/data/utilities.py
scaae/models/__init__.py
scaae/models/aae.py
scaae/models/base.py
scaae/models/distributions.py
scaae/models/noise_models.py
scaae/models/utilities.py
scaae-0.2.0a0.dist-info/entry_points.txt
scaae-0.2.0a0.dist-info/LICENSE
scaae-0.2.0a0.dist-info/WHEEL
scaae-0.2.0a0.dist-info/METADATA
scaae-0.2.0a0.dist-info/RECORD
