Metadata-Version: 2.1
Name: scaae
Version: 0.2.0a0
Summary: Adversarial auto-encoders for single-cell transcriptomics.
Author-email: Christopher Heje Grønbech <christopher.gronbech@bio.ku.dk>
Requires-Python: >= 3.7, < 3.11
Classifier: Programming Language :: Python :: 3
Classifier: License :: OSI Approved :: MIT License
Classifier: Operating System :: OS Independent
Requires-Dist: anndata >= 0.7
Requires-Dist: matplotlib >= 3.6
Requires-Dist: natsort >= 8.4
Requires-Dist: numpy >= 1.19
Requires-Dist: pandas >= 1.4
Requires-Dist: plotly >= 5.17
Requires-Dist: scanpy[louvain,leiden] >= 1.8
Requires-Dist: scipy >= 1.10
Requires-Dist: scikit-learn >= 1.3
Requires-Dist: seaborn >= 0.12
Requires-Dist: tensorflow >= 2.4, < 2.14
Requires-Dist: tensorflow_probability >= 0.12, < 0.22
Requires-Dist: tqdm
Requires-Dist: cudf-cu11 >= 23.10 ; extra == "rapids"
Requires-Dist: cuml-cu11 >= 23.10 ; extra == "rapids"
Requires-Dist: cugraph-cu11 >= 23.10 ; extra == "rapids"
Provides-Extra: rapids
